[
  {
    "id": 13,
    "name": "나무 방패",
    "grade": "COMMON",
    "type": "EQUIPMENT",
    "slot": "SUB_WEAPON",
    "subType": "SHIELD",
    "twoHanded": false,
    "description": "화살이나 가벼운 타격을 막기에 적합합니다.",
    "price": 35000,
    "icon": "/images/items/13.png",
    "baseStatsBonus": {},
    "combatStatsBonus": {
      "physDef": 3.0,
      "dodge": -2.0,
      "statusResist": 2.0
    },
    "grantedSkillIds": []
  },
  {
    "id": 18,
    "name": "원소의 서 [초급]",
    "grade": "RARE",
    "type": "EQUIPMENT",
    "slot": "SUB_WEAPON",
    "subType": "BOOK",
    "twoHanded": false,
    "description": "기초적인 삼원소 마법이 기록된 마법서입니다. 마나의 흐름을 정돈하여 영창을 돕습니다.",
    "price": 520000,
    "icon": "/images/items/18.png",
    "baseStatsBonus": {
      "4": 5.0,
      "8": 5.0,
      "13": 5.0
    },
    "combatStatsBonus": {
      "magicAtk": 5.0,
      "maxMp": 20.0,
      "mpRegen": 0.5,
      "accuracy": 3.0
    },
    "grantedSkillIds": [24, 25, 26]
  },
  {
    "id": 50,
    "name": "불꽃의 기초 이론",
    "grade": "UNCOMMON",
    "type": "EQUIPMENT",
    "slot": "SUB_WEAPON",
    "subType": "GRIMORE",
    "description": "화염 마법의 입문서입니다. 책장마다 그을린 흔적이 남아있습니다.",
    "price": 250000,
    "icon": "/images/items/50.png",
    "baseStatsBonus": { "13": 6.0 },
    "combatStatsBonus": { "fireAtk": 15.0, "fireRes": 5.0, "maxMp": 30.0 },
    "grantedSkillIds": [201]
  },
  {
    "id": 51,
    "name": "타오르는 페이지",
    "grade": "RARE",
    "type": "EQUIPMENT",
    "slot": "SUB_WEAPON",
    "subType": "GRIMORE",
    "description": "스스로 열기를 내뿜는 마도서입니다. 숙련된 화염 마법사가 애용합니다.",
    "price": 550000,
    "icon": "/images/items/51.png",
    "baseStatsBonus": { "13": 12.0, "14": 8.0 },
    "combatStatsBonus": { "fireAtk": 40.0, "fireRes": 15.0, "magicAtk": 10.0 },
    "grantedSkillIds": [202]
  },
  {
    "id": 52,
    "name": "적염의 영창기록",
    "grade": "RARE",
    "type": "EQUIPMENT",
    "slot": "SUB_WEAPON",
    "subType": "GRIMORE",
    "description": "폭발적인 화력을 끌어내기 위한 고위 마법사의 연구 노트입니다.",
    "price": 580000,
    "icon": "/images/items/52.png",
    "baseStatsBonus": { "13": 15.0, "20": 5.0 },
    "combatStatsBonus": { "fireAtk": 50.0, "fireRes": 10.0, "mpRegen": 1.5 },
    "grantedSkillIds": [203]
  },
  {
    "id": 53,
    "name": "만년설의 편린",
    "grade": "UNCOMMON",
    "type": "EQUIPMENT",
    "slot": "SUB_WEAPON",
    "subType": "GRIMORE",
    "description": "만지면 손끝이 아릴 정도로 차가운 기운이 서린 책입니다.",
    "price": 260000,
    "icon": "/images/items/53.png",
    "baseStatsBonus": { "14": 7.0 },
    "combatStatsBonus": { "iceAtk": 18.0, "iceRes": 8.0, "maxMp": 20.0 },
    "grantedSkillIds": [211]
  },
  {
    "id": 54,
    "name": "서리 맺힌 마법서",
    "grade": "RARE",
    "type": "EQUIPMENT",
    "slot": "SUB_WEAPON",
    "subType": "GRIMORE",
    "description": "냉기 마법의 정수를 담고 있습니다. 주변 공기를 차갑게 식힙니다.",
    "price": 560000,
    "icon": "/images/items/54.png",
    "baseStatsBonus": { "14": 15.0, "18": 5.0 },
    "combatStatsBonus": { "iceAtk": 45.0, "iceRes": 20.0, "physDef": 15.0 },
    "grantedSkillIds": [212]
  },
  {
    "id": 55,
    "name": "절대영도의 고서",
    "grade": "RARE",
    "type": "EQUIPMENT",
    "slot": "SUB_WEAPON",
    "subType": "GRIMORE",
    "description": "빙하의 심층부에서 발견된 지식이 기록되어 있습니다.",
    "price": 600000,
    "icon": "/images/items/55.png",
    "baseStatsBonus": { "13": 10.0, "14": 15.0 },
    "combatStatsBonus": { "iceAtk": 55.0, "iceRes": 15.0, "statusResist": 10.0 },
    "grantedSkillIds": [213]
  },
  {
    "id": 56,
    "name": "전류의 흐름",
    "grade": "UNCOMMON",
    "type": "EQUIPMENT",
    "slot": "SUB_WEAPON",
    "subType": "GRIMORE",
    "description": "미세한 정전기가 흐르는 마법서입니다. 전격 마법의 기초를 다룹니다.",
    "price": 270000,
    "icon": "/images/items/56.png",
    "baseStatsBonus": { "20": 6.0 },
    "combatStatsBonus": { "lightningAtk": 20.0, "lightningRes": 5.0, "moveSpeed": 0.05 },
    "grantedSkillIds": [221]
  },
  {
    "id": 57,
    "name": "폭풍우의 영창 소망",
    "grade": "RARE",
    "type": "EQUIPMENT",
    "slot": "SUB_WEAPON",
    "subType": "GRIMORE",
    "description": "뇌운의 힘을 종이 위에 붙들어 매어놓은 마도서입니다.",
    "price": 570000,
    "icon": "/images/items/57.png",
    "baseStatsBonus": { "13": 10.0, "20": 10.0 },
    "combatStatsBonus": { "lightningAtk": 48.0, "lightningRes": 15.0, "critRate": 5.0 },
    "grantedSkillIds": [222]
  },
  {
    "id": 58,
    "name": "청천벽력의 서",
    "grade": "RARE",
    "type": "EQUIPMENT",
    "slot": "SUB_WEAPON",
    "subType": "GRIMORE",
    "description": "찰나의 순간에 강력한 전류를 방출하는 법이 기록되어 있습니다.",
    "price": 620000,
    "icon": "/images/items/58.png",
    "baseStatsBonus": { "13": 12.0, "21": 8.0 },
    "combatStatsBonus": { "lightningAtk": 60.0, "lightningRes": 10.0, "accuracy": 5.0 },
    "grantedSkillIds": [223]
  },
  {
    "id": 59,
    "name": "대지의 울림",
    "grade": "UNCOMMON",
    "type": "EQUIPMENT",
    "slot": "SUB_WEAPON",
    "subType": "GRIMORE",
    "description": "두꺼운 가죽으로 장정된 무거운 마법서입니다. 땅의 기운이 느껴집니다.",
    "price": 240000,
    "icon": "/images/items/59.png",
    "baseStatsBonus": { "1": 8.0 },
    "combatStatsBonus": { "earthAtk": 15.0, "earthRes": 15.0, "physDef": 10.0 },
    "grantedSkillIds": [231]
  },
  {
    "id": 60,
    "name": "수호령의 토템북",
    "grade": "RARE",
    "type": "EQUIPMENT",
    "slot": "SUB_WEAPON",
    "subType": "GRIMORE",
    "description": "고대 부족의 지혜가 담긴 서적입니다. 자연과의 교감을 돕습니다.",
    "price": 530000,
    "icon": "/images/items/60.png",
    "baseStatsBonus": { "1": 15.0, "2": 10.0 },
    "combatStatsBonus": { "earthAtk": 40.0, "earthRes": 25.0, "hpRegen": 5.0 },
    "grantedSkillIds": [232]
  },
  {
    "id": 61,
    "name": "지각 변동의 기록",
    "grade": "RARE",
    "type": "EQUIPMENT",
    "slot": "SUB_WEAPON",
    "subType": "GRIMORE",
    "description": "거대한 산맥의 움직임을 관찰하여 기록한 대마도서의 필사본입니다.",
    "price": 550000,
    "icon": "/images/items/61.png",
    "baseStatsBonus": { "1": 20.0, "13": 5.0 },
    "combatStatsBonus": { "earthAtk": 55.0, "earthRes": 20.0, "physRes": 10.0 },
    "grantedSkillIds": [233]
  },
  {
    "id": 62,
    "name": "성스러운 경전",
    "grade": "UNCOMMON",
    "type": "EQUIPMENT",
    "slot": "SUB_WEAPON",
    "subType": "GRIMORE",
    "description": "은은한 빛을 내는 경전입니다. 신성한 마력의 흐름을 정돈합니다.",
    "price": 300000,
    "icon": "/images/items/62.png",
    "baseStatsBonus": { "4": 8.0 },
    "combatStatsBonus": { "holyAtk": 15.0, "holyRes": 10.0, "hpRegen": 2.0 },
    "grantedSkillIds": [241]
  },
  {
    "id": 63,
    "name": "사제단의 기도문",
    "grade": "RARE",
    "type": "EQUIPMENT",
    "slot": "SUB_WEAPON",
    "subType": "GRIMORE",
    "description": "수많은 사제들의 기도가 깃들어 있습니다. 악한 기운을 물리칩니다.",
    "price": 650000,
    "icon": "/images/items/63.png",
    "baseStatsBonus": { "4": 15.0, "13": 10.0 },
    "combatStatsBonus": { "holyAtk": 45.0, "holyRes": 25.0, "statusResist": 15.0 },
    "grantedSkillIds": [242]
  },
  {
    "id": 64,
    "name": "대천사의 계시록",
    "grade": "RARE",
    "type": "EQUIPMENT",
    "slot": "SUB_WEAPON",
    "subType": "GRIMORE",
    "description": "고결한 신성력이 깃들어 있어, 자격이 없는 자는 읽을 수 없습니다.",
    "price": 700000,
    "icon": "/images/items/64.png",
    "baseStatsBonus": { "4": 20.0, "14": 5.0 },
    "combatStatsBonus": { "holyAtk": 60.0, "holyRes": 20.0, "darkRes": 20.0 },
    "grantedSkillIds": [243]
  },
  {
    "id": 65,
    "name": "그림자 영창법",
    "grade": "UNCOMMON",
    "type": "EQUIPMENT",
    "slot": "SUB_WEAPON",
    "subType": "GRIMORE",
    "description": "어둠 속에 숨어 영창하는 비법이 담겨 있습니다.",
    "price": 280000,
    "icon": "/images/items/65.png",
    "baseStatsBonus": { "13": 8.0 },
    "combatStatsBonus": { "darkAtk": 20.0, "darkRes": 10.0, "dodge": 3.0 },
    "grantedSkillIds": [251]
  },
  {
    "id": 66,
    "name": "심연의 필사본",
    "grade": "RARE",
    "type": "EQUIPMENT",
    "slot": "SUB_WEAPON",
    "subType": "GRIMORE",
    "description": "빛조차 삼켜버리는 심연의 지식이 기록된 두루마리 책입니다.",
    "price": 630000,
    "icon": "/images/items/66.png",
    "baseStatsBonus": { "13": 15.0, "15": 10.0 },
    "combatStatsBonus": { "darkAtk": 50.0, "darkRes": 20.0, "magRes": 10.0 },
    "grantedSkillIds": [252]
  },
  {
    "id": 67,
    "name": "밤의 지배자",
    "grade": "RARE",
    "type": "EQUIPMENT",
    "slot": "SUB_WEAPON",
    "subType": "GRIMORE",
    "description": "어둠을 다스리는 자들을 위해 쓰여진 금기된 마법서 중 하나입니다.",
    "price": 680000,
    "icon": "/images/items/67.png",
    "baseStatsBonus": { "13": 20.0, "20": 5.0 },
    "combatStatsBonus": { "darkAtk": 65.0, "darkRes": 15.0, "magicAtk": 15.0 },
    "grantedSkillIds": [253]
  },
  {
    "id": 68,
    "name": "광신의 단편",
    "grade": "UNCOMMON",
    "type": "EQUIPMENT",
    "slot": "SUB_WEAPON",
    "subType": "GRIMORE",
    "description": "알 수 없는 기괴한 문자로 가득 찬 책입니다. 보기만 해도 정신이 혼미해집니다.",
    "price": 320000,
    "icon": "/images/items/68.png",
    "baseStatsBonus": { "13": 10.0 },
    "combatStatsBonus": { "chaosAtk": 25.0, "chaosRes": 5.0, "maxMp": 50.0 },
    "grantedSkillIds": [261]
  },
  {
    "id": 69,
    "name": "외신의 속삭임",
    "grade": "RARE",
    "type": "EQUIPMENT",
    "slot": "SUB_WEAPON",
    "subType": "GRIMORE",
    "description": "차원을 넘어온 불길한 지식이 담겨 있습니다. 이교도들이 목숨처럼 아낍니다.",
    "price": 720000,
    "icon": "/images/items/69.png",
    "baseStatsBonus": { "13": 20.0, "9": 5.0 },
    "combatStatsBonus": { "chaosAtk": 55.0, "chaosRes": 15.0, "critDmg": 15.0 },
    "grantedSkillIds": [262]
  },
  {
    "id": 70,
    "name": "혼돈의 마도 대전",
    "grade": "RARE",
    "type": "EQUIPMENT",
    "slot": "SUB_WEAPON",
    "subType": "GRIMORE",
    "description": "세계의 질서를 뒤흔드는 혼돈 마법의 정수를 모아둔 책입니다.",
    "price": 750000,
    "icon": "/images/items/70.png",
    "baseStatsBonus": { "13": 25.0 },
    "combatStatsBonus": { "chaosAtk": 70.0, "chaosRes": 20.0, "mpRegen": 2.0 },
    "grantedSkillIds": [263]
  },
  {
    "id": 71,
    "name": "독성 화합물의 이해",
    "grade": "UNCOMMON",
    "type": "EQUIPMENT",
    "slot": "SUB_WEAPON",
    "subType": "GRIMORE",
    "description": "치명적인 독을 추출하고 가공하는 법이 적힌 연구서입니다.",
    "price": 230000,
    "icon": "/images/items/71.png",
    "baseStatsBonus": { "3": 8.0 },
    "combatStatsBonus": { "toxicAtk": 20.0, "toxicRes": 10.0, "accuracy": 3.0 },
    "grantedSkillIds": [271]
  },
  {
    "id": 72,
    "name": "역병의 전말",
    "grade": "RARE",
    "type": "EQUIPMENT",
    "slot": "SUB_WEAPON",
    "subType": "GRIMORE",
    "description": "과거 대륙을 휩쓸었던 역병의 기록과 이를 마법적으로 구현하는 법이 담겨 있습니다.",
    "price": 540000,
    "icon": "/images/items/72.png",
    "baseStatsBonus": { "3": 15.0, "13": 10.0 },
    "combatStatsBonus": { "toxicAtk": 50.0, "toxicRes": 25.0, "statusResist": 10.0 },
    "grantedSkillIds": [272]
  },
  {
    "id": 73,
    "name": "매드 사이언티스트의 비망록",
    "grade": "RARE",
    "type": "EQUIPMENT",
    "slot": "SUB_WEAPON",
    "subType": "GRIMORE",
    "description": "광기에 사로잡힌 학자가 남긴 기록입니다. 독의 효능을 극대화하는 법이 적혀 있습니다.",
    "price": 590000,
    "icon": "/images/items/73.png",
    "baseStatsBonus": { "3": 20.0, "17": 5.0 },
    "combatStatsBonus": { "toxicAtk": 65.0, "toxicRes": 20.0, "critRate": 7.0 },
    "grantedSkillIds": [273]
  },
  {
    "id": 80,
    "name": "철제 카이트 실드",
    "grade": "UNCOMMON",
    "type": "EQUIPMENT",
    "slot": "SUB_WEAPON",
    "subType": "SHIELD",
    "twoHanded": false,
    "description": "기사들이 흔히 사용하는 눈물방울 모양의 철제 방패입니다. 물리적인 타격을 막아내는 데 최적화되어 있습니다.",
    "price": 320000,
    "icon": "/images/items/80.png",
    "baseStatsBonus": {
      "1": 4.0,
      "2": 2.0
    },
    "combatStatsBonus": {
      "physDef": 15.0,
      "physRes": 8.0,
      "magRes": 3.0,
      "dodge": -5.0,
      "statusResist": 5.0
    },
    "grantedSkillIds": []
  },
  {
    "id": 81,
    "name": "룬 각인 라운드 실드",
    "grade": "UNCOMMON",
    "type": "EQUIPMENT",
    "slot": "SUB_WEAPON",
    "subType": "SHIELD",
    "twoHanded": false,
    "description": "가장자리에 마력 억제 룬이 새겨진 방패입니다. 물리 방어력은 낮지만 마법 공격의 충격을 완화합니다.",
    "price": 350000,
    "icon": "/images/items/81.png",
    "baseStatsBonus": {
      "13": 3.0,
      "14": 3.0
    },
    "combatStatsBonus": {
      "physDef": 8.0,
      "physRes": 3.0,
      "magRes": 12.0,
      "dodge": -2.0,
      "statusResist": 8.0
    },
    "grantedSkillIds": []
  },
  {
    "id": 82,
    "name": "가시 돋친 버클러",
    "grade": "UNCOMMON",
    "type": "EQUIPMENT",
    "slot": "SUB_WEAPON",
    "subType": "SHIELD",
    "twoHanded": false,
    "description": "공격적인 운용이 가능한 소형 방패입니다. 방어 면적은 좁지만, 적의 공격을 쳐내며 역습할 기회를 만듭니다.",
    "price": 290000,
    "icon": "/images/items/82.png",
    "baseStatsBonus": {
      "10": 3.0,
      "20": 5.0
    },
    "combatStatsBonus": {
      "physDef": 5.0,
      "physRes": 4.0,
      "dodge": 2.0,
      "meleeAtk": 5.0,
      "critRate": 3.0
    },
    "grantedSkillIds": []
  },
  {
    "id": 83,
    "name": "성기사의 타워 실드",
    "grade": "RARE",
    "type": "EQUIPMENT",
    "slot": "SUB_WEAPON",
    "subType": "SHIELD",
    "twoHanded": false,
    "description": "전신을 가릴 수 있을 정도로 거대한 강철 방패입니다. 움직임은 둔해지지만 철벽 같은 방어력을 제공합니다.",
    "price": 1050000,
    "icon": "/images/items/83.png",
    "baseStatsBonus": {
      "1": 15.0,
      "2": 10.0
    },
    "combatStatsBonus": {
      "physDef": 75.0,
      "physRes": 22.0,
      "magRes": 10.0,
      "dodge": -15.0,
      "moveSpeed": -0.15,
      "statusResist": 20.0
    },
    "grantedSkillIds": []
  },
  {
    "id": 84,
    "name": "거울빛 연마 방패",
    "grade": "RARE",
    "type": "EQUIPMENT",
    "slot": "SUB_WEAPON",
    "subType": "SHIELD",
    "twoHanded": false,
    "description": "표면이 거울처럼 매끄럽게 닦인 은제 방패입니다. 적의 마법 투사체를 튕겨낼 듯한 광택이 흐릅니다.",
    "price": 1120000,
    "icon": "/images/items/84.png",
    "baseStatsBonus": {
      "13": 12.0,
      "14": 13.0
    },
    "combatStatsBonus": {
      "physDef": 55.0,
      "physRes": 12.0,
      "magRes": 25.0,
      "mpRegen": 2.0,
      "dodge": -5.0
    },
    "grantedSkillIds": []
  },
  {
    "id": 85,
    "name": "스파이크 실드",
    "grade": "RARE",
    "type": "EQUIPMENT",
    "slot": "SUB_WEAPON",
    "subType": "SHIELD",
    "twoHanded": false,
    "description": "방패 전면에 무수히 많은 가시가 돋아나 있습니다. 방어 시에도 적에게 상처를 입히지만, 무게 중심이 쏠려 있어 다루기 까다롭습니다.",
    "price": 1080000,
    "icon": "/images/items/85.png",
    "baseStatsBonus": {
      "10": 15.0,
      "20": 10.0
    },
    "combatStatsBonus": {
      "meleeAtk": 25.0,
      "physDef": 50.0,
      "physRes": 15.0,
      "bleedPen": 20.0,
      "accuracy": -5.0,
      "maxStamina": -20.0
    },
    "grantedSkillIds": []
  },
  {
    "id": 30000,
    "name": "불굴의 요새 성벽 방패",
    "grade": "EPIC",
    "type": "EQUIPMENT",
    "slot": "SUB_WEAPON",
    "subType": "SHIELD",
    "twoHanded": false,
    "description": "전설적인 중갑 기사가 사용했다고 전해지는 거대 방패입니다. 웬만한 공성 병기의 타격도 가뿐히 견뎌내며, 착용자를 움직이는 요새로 만들어줍니다.",
    "price": 2500000,
    "icon": "/images/items/30000.png",
    "baseStatsBonus": {
      "1": 35.0,
      "2": 15.0
    },
    "combatStatsBonus": {
      "physDef": 150.0,
      "physRes": 45.0,
      "magRes": 20.0,
      "statusResist": 25.0,
      "moveSpeed": -0.2,
      "dodge": -15.0
    },
    "grantedSkillIds": []
  },
  {
    "id": 30001,
    "name": "거신병의 무력화 방패",
    "grade": "EPIC",
    "type": "EQUIPMENT",
    "slot": "SUB_WEAPON",
    "subType": "SHIELD",
    "twoHanded": false,
    "description": "순수한 완력으로 적을 짓누르기 위해 설계된 투박한 철제 방패입니다. 방어보다는 적의 자세를 무너뜨리고 뼈를 으스러뜨리는 용도에 특화되어 있습니다.",
    "price": 2350000,
    "icon": "/images/items/30001.png",
    "baseStatsBonus": {
      "10": 40.0,
      "1": 10.0
    },
    "combatStatsBonus": {
      "meleeAtk": 40.0,
      "physDef": 85.0,
      "physPen": 15.0,
      "critDmg": 20.0,
      "accuracy": -5.0,
      "maxStamina": 30.0
    },
    "grantedSkillIds": []
  },
  {
    "id": 30002,
    "name": "바람을 가르는 용병의 버클러",
    "grade": "EPIC",
    "type": "EQUIPMENT",
    "slot": "SUB_WEAPON",
    "subType": "SHIELD",
    "twoHanded": false,
    "description": "민첩한 용병들이 선호하는 특수 합금 방패입니다. 무게가 거의 느껴지지 않을 정도로 가벼우며, 적의 공격을 쳐냄과 동시에 치명적인 반격을 가할 수 있습니다.",
    "price": 2400000,
    "icon": "/images/items/30002.png",
    "baseStatsBonus": {
      "20": 35.0,
      "21": 15.0
    },
    "combatStatsBonus": {
      "physDef": 60.0,
      "dodge": 15.0,
      "moveSpeed": 0.25,
      "critRate": 12.0,
      "accuracy": 10.0,
      "meleeAtk": 25.0
    },
    "grantedSkillIds": []
  },
  {
    "id": 30003,
    "name": "균형의 전사단 대형 방패",
    "grade": "EPIC",
    "type": "EQUIPMENT",
    "slot": "SUB_WEAPON",
    "subType": "SHIELD",
    "twoHanded": false,
    "description": "강력한 힘과 재빠른 움직임을 동시에 요구하는 베테랑 전사들을 위한 방패입니다. 공방의 조화가 완벽하여 어떠한 전투 상황에서도 최적의 효율을 보여줍니다.",
    "price": 2600000,
    "icon": "/images/items/30003.png",
    "baseStatsBonus": {
      "10": 25.0,
      "20": 25.0
    },
    "combatStatsBonus": {
      "physDef": 110.0,
      "physRes": 25.0,
      "meleeAtk": 30.0,
      "dodge": 5.0,
      "maxHp": 150.0,
      "maxStamina": 50.0
    },
    "grantedSkillIds": []
  },
  {
    "id": 30005,
    "name": "불가침의 성벽 - 아다만티움",
    "grade": "LEGENDARY",
    "type": "EQUIPMENT",
    "slot": "SUB_WEAPON",
    "subType": "SHIELD",
    "twoHanded": false,
    "description": "전설적인 대장장이가 신의 금속을 녹여 만든 거대 방패입니다. 이 방패 뒤에 선 자는 그 어떤 재앙 앞에서도 결코 흔들리지 않습니다.",
    "price": 25000000,
    "icon": "/images/items/30005.png",
    "baseStatsBonus": {
      "1": 45.0,
      "2": 25.0
    },
    "combatStatsBonus": {
      "physDef": 350.0,
      "physRes": 80.0,
      "magRes": 50.0,
      "statusResist": 40.0,
      "moveSpeed": -0.2,
      "dodge": -25.0,
      "hpRegen": 15.0
    },
    "grantedSkillIds": []
  },
  {
    "id": 30006,
    "name": "파괴신의 철퇴 방패",
    "grade": "LEGENDARY",
    "type": "EQUIPMENT",
    "slot": "SUB_WEAPON",
    "subType": "SHIELD",
    "twoHanded": false,
    "description": "방어보다 파괴에 목적을 둔 흉물스러운 강철판입니다. 휘두르는 것만으로도 적의 갑옷과 뼈를 동시에 가루로 만듭니다.",
    "price": 22000000,
    "icon": "/images/items/30006.png",
    "baseStatsBonus": {
      "10": 60.0,
      "1": 20.0
    },
    "combatStatsBonus": {
      "meleeAtk": 120.0,
      "physPen": 45.0,
      "physDef": 180.0,
      "physRes": 30.0,
      "accuracy": -10.0,
      "critDmg": 30.0
    },
    "grantedSkillIds": []
  },
  {
    "id": 30007,
    "name": "은영의 날개 버클러",
    "grade": "LEGENDARY",
    "type": "EQUIPMENT",
    "slot": "SUB_WEAPON",
    "subType": "SHIELD",
    "twoHanded": false,
    "description": "빛조차 투과할 듯 가벼운 신비한 합금으로 제작되었습니다. 방패라기보다는 착용자의 움직임을 보조하는 날개에 가깝습니다.",
    "price": 24000000,
    "icon": "/images/items/30007.png",
    "baseStatsBonus": {
      "20": 55.0,
      "21": 25.0
    },
    "combatStatsBonus": {
      "dodge": 35.0,
      "moveSpeed": 0.4,
      "physDef": 80.0,
      "critRate": 15.0,
      "accuracy": 20.0,
      "maxStamina": 100.0
    },
    "grantedSkillIds": []
  },
  {
    "id": 30008,
    "name": "패왕의 권위",
    "grade": "LEGENDARY",
    "type": "EQUIPMENT",
    "slot": "SUB_WEAPON",
    "subType": "SHIELD",
    "twoHanded": false,
    "description": "무력과 기민함을 모두 갖춘 군주만이 다룰 수 있는 문장 방패입니다. 공방의 완벽한 조화를 상징합니다.",
    "price": 28000000,
    "icon": "/images/items/30008.png",
    "baseStatsBonus": {
      "10": 40.0,
      "20": 40.0
    },
    "combatStatsBonus": {
      "meleeAtk": 70.0,
      "physDef": 220.0,
      "physRes": 40.0,
      "dodge": 10.0,
      "critRate": 10.0,
      "statusResist": 25.0,
      "moveSpeed": 0.1
    },
    "grantedSkillIds": []
  },
  {
    "id": 30100,
    "name": "홍련의 대마법서",
    "grade": "EPIC",
    "type": "EQUIPMENT",
    "slot": "SUB_WEAPON",
    "subType": "GRIMORE",
    "description": "궁극의 화염 영창법이 기록된 서적입니다. 책장을 넘길 때마다 불꽃이 일렁입니다.",
    "price": 2500000,
    "icon": "/images/items/30100.png",
    "baseStatsBonus": { "13": 25.0, "14": 15.0 },
    "combatStatsBonus": { "fireAtk": 120.0, "fireRes": 40.0, "magicAtk": 35.0 },
    "grantedSkillIds": []
  },
  {
    "id": 30101,
    "name": "이그니스의 심장 기록",
    "grade": "EPIC",
    "type": "EQUIPMENT",
    "slot": "SUB_WEAPON",
    "subType": "GRIMORE",
    "description": "불의 정령왕의 심장에서 추출한 마력을 종이에 박아 넣었습니다.",
    "price": 2750000,
    "icon": "/images/items/30101.png",
    "baseStatsBonus": { "13": 30.0, "20": 10.0 },
    "combatStatsBonus": { "fireAtk": 140.0, "fireRes": 30.0, "maxMp": 150.0 },
    "grantedSkillIds": []
  },
  {
    "id": 30102,
    "name": "연옥의 잔불 페이지",
    "grade": "EPIC",
    "type": "EQUIPMENT",
    "slot": "SUB_WEAPON",
    "subType": "GRIMORE",
    "description": "꺼지지 않는 연옥의 불꽃을 형상화했습니다. 화염 마술사들의 성유물입니다.",
    "price": 2800000,
    "icon": "/images/items/30102.png",
    "baseStatsBonus": { "13": 35.0, "10": 10.0 },
    "combatStatsBonus": { "fireAtk": 160.0, "fireRes": 25.0, "critRate": 10.0 },
    "grantedSkillIds": []
  },
  {
    "id": 30103,
    "name": "영구동토의 고대문서",
    "grade": "EPIC",
    "type": "EQUIPMENT",
    "slot": "SUB_WEAPON",
    "subType": "GRIMORE",
    "description": "수만 년 전 얼어붙은 비술이 담겨 있습니다. 주위의 습기를 즉각 얼려버립니다.",
    "price": 2450000,
    "icon": "/images/items/30103.png",
    "baseStatsBonus": { "14": 30.0, "1": 15.0 },
    "combatStatsBonus": { "iceAtk": 110.0, "iceRes": 50.0, "physDef": 45.0 },
    "grantedSkillIds": []
  },
  {
    "id": 30104,
    "name": "빙결의 마녀가 남긴 시",
    "grade": "EPIC",
    "type": "EQUIPMENT",
    "slot": "SUB_WEAPON",
    "subType": "GRIMORE",
    "description": "아름답지만 차가운 마력이 깃들어 있습니다. 냉기 법사들의 로망이라 불립니다.",
    "price": 2600000,
    "icon": "/images/items/30104.png",
    "baseStatsBonus": { "14": 25.0, "13": 20.0 },
    "combatStatsBonus": { "iceAtk": 130.0, "iceRes": 40.0, "statusResist": 25.0 },
    "grantedSkillIds": []
  },
  {
    "id": 30105,
    "name": "극지방의 성운 기록",
    "grade": "EPIC",
    "type": "EQUIPMENT",
    "slot": "SUB_WEAPON",
    "subType": "GRIMORE",
    "description": "오로라의 마나를 정제하여 기록한 마도서입니다. 정신을 극한까지 맑게 합니다.",
    "price": 2700000,
    "icon": "/images/items/30105.png",
    "baseStatsBonus": { "14": 35.0, "21": 15.0 },
    "combatStatsBonus": { "iceAtk": 150.0, "iceRes": 35.0, "mpRegen": 4.5 },
    "grantedSkillIds": []
  },
  {
    "id": 30106,
    "name": "청뢰의 징벌서",
    "grade": "EPIC",
    "type": "EQUIPMENT",
    "slot": "SUB_WEAPON",
    "subType": "GRIMORE",
    "description": "하늘의 분노를 종이에 봉인했습니다. 전격 마법의 속도가 비약적으로 상승합니다.",
    "price": 2650000,
    "icon": "/images/items/30106.png",
    "baseStatsBonus": { "20": 30.0, "13": 15.0 },
    "combatStatsBonus": { "lightningAtk": 140.0, "lightningRes": 30.0, "moveSpeed": 0.2 },
    "grantedSkillIds": []
  },
  {
    "id": 30107,
    "name": "폭풍우를 부르는 영창",
    "grade": "EPIC",
    "type": "EQUIPMENT",
    "slot": "SUB_WEAPON",
    "subType": "GRIMORE",
    "description": "대기를 가르는 번개의 진동이 책 전체에서 느껴집니다.",
    "price": 2700000,
    "icon": "/images/items/30107.png",
    "baseStatsBonus": { "20": 25.0, "21": 15.0, "13": 10.0 },
    "combatStatsBonus": { "lightningAtk": 155.0, "lightningRes": 25.0, "critRate": 12.0 },
    "grantedSkillIds": []
  },
  {
    "id": 30108,
    "name": "테슬라의 유실된 연구",
    "grade": "EPIC",
    "type": "EQUIPMENT",
    "slot": "SUB_WEAPON",
    "subType": "GRIMORE",
    "description": "미지의 번개 원리가 기록되어 있습니다. 인공적인 마찰 마나를 생성합니다.",
    "price": 2900000,
    "icon": "/images/items/30108.png",
    "baseStatsBonus": { "20": 40.0, "9": 10.0 },
    "combatStatsBonus": { "lightningAtk": 170.0, "lightningRes": 20.0, "accuracy": 15.0 },
    "grantedSkillIds": []
  },
  {
    "id": 30109,
    "name": "대지의 맥동 기록",
    "grade": "EPIC",
    "type": "EQUIPMENT",
    "slot": "SUB_WEAPON",
    "subType": "GRIMORE",
    "description": "거대한 산맥의 뿌리를 관통하는 마나를 기록한 서적입니다.",
    "price": 2400000,
    "icon": "/images/items/30109.png",
    "baseStatsBonus": { "1": 30.0, "11": 15.0 },
    "combatStatsBonus": { "earthAtk": 120.0, "earthRes": 60.0, "physRes": 25.0 },
    "grantedSkillIds": []
  },
  {
    "id": 30110,
    "name": "고대 토템의 마도 실사본",
    "grade": "EPIC",
    "type": "EQUIPMENT",
    "slot": "SUB_WEAPON",
    "subType": "GRIMORE",
    "description": "대지술사들의 지혜가 담긴 영창 기록입니다. 자연의 가호를 불러옵니다.",
    "price": 2550000,
    "icon": "/images/items/30110.png",
    "baseStatsBonus": { "1": 25.0, "4": 25.0 },
    "combatStatsBonus": { "earthAtk": 135.0, "earthRes": 45.0, "hpRegen": 12.0 },
    "grantedSkillIds": []
  },
  {
    "id": 30111,
    "name": "인디언 수령의 환상록",
    "grade": "EPIC",
    "type": "EQUIPMENT",
    "slot": "SUB_WEAPON",
    "subType": "GRIMORE",
    "description": "땅의 정령과 대화하는 법이 적혀 있습니다. 소지한 것만으로 몸이 단단해집니다.",
    "price": 2650000,
    "icon": "/images/items/30111.png",
    "baseStatsBonus": { "1": 40.0, "10": 10.0 },
    "combatStatsBonus": { "earthAtk": 150.0, "earthRes": 40.0, "physDef": 70.0 },
    "grantedSkillIds": []
  },
  {
    "id": 30112,
    "name": "성스러운 예언의 서",
    "grade": "EPIC",
    "type": "EQUIPMENT",
    "slot": "SUB_WEAPON",
    "subType": "GRIMORE",
    "description": "고위 신성사제들만이 열람할 수 있는 경전입니다. 눈부신 빛을 발산합니다.",
    "price": 3100000,
    "icon": "/images/items/30112.png",
    "baseStatsBonus": { "4": 30.0, "13": 20.0 },
    "combatStatsBonus": { "holyAtk": 125.0, "holyRes": 50.0, "maxMp": 200.0 },
    "grantedSkillIds": []
  },
  {
    "id": 30113,
    "name": "대천사의 영광 찬가",
    "grade": "EPIC",
    "type": "EQUIPMENT",
    "slot": "SUB_WEAPON",
    "subType": "GRIMORE",
    "description": "하늘의 선율을 옮겨 적은 마법서입니다. 모든 악한 기운을 정화합니다.",
    "price": 3300000,
    "icon": "/images/items/30113.png",
    "baseStatsBonus": { "4": 40.0, "14": 10.0 },
    "combatStatsBonus": { "holyAtk": 145.0, "holyRes": 45.0, "statusResist": 35.0 },
    "grantedSkillIds": []
  },
  {
    "id": 30114,
    "name": "바티칸의 기밀 마도서",
    "grade": "EPIC",
    "type": "EQUIPMENT",
    "slot": "SUB_WEAPON",
    "subType": "GRIMORE",
    "description": "외부에 알려지지 않은 강력한 치유와 빛의 권능이 수록되어 있습니다.",
    "price": 3500000,
    "icon": "/images/items/30114.png",
    "baseStatsBonus": { "4": 35.0, "1": 15.0 },
    "combatStatsBonus": { "holyAtk": 160.0, "holyRes": 40.0, "hpRegen": 15.0 },
    "grantedSkillIds": []
  },
  {
    "id": 30115,
    "name": "심연을 걷는 자의 기록",
    "grade": "EPIC",
    "type": "EQUIPMENT",
    "slot": "SUB_WEAPON",
    "subType": "GRIMORE",
    "description": "어둠 그 자체가 된 마법사가 남긴 유물입니다. 빛을 거부합니다.",
    "price": 2800000,
    "icon": "/images/items/30115.png",
    "baseStatsBonus": { "13": 35.0, "15": 15.0 },
    "combatStatsBonus": { "darkAtk": 130.0, "darkRes": 45.0, "magicAtk": 50.0 },
    "grantedSkillIds": []
  },
  {
    "id": 30116,
    "name": "밤의 지배자 찬가",
    "grade": "EPIC",
    "type": "EQUIPMENT",
    "slot": "SUB_WEAPON",
    "subType": "GRIMORE",
    "description": "달빛조차 없는 밤에 쓰여진 글귀들이 불길한 오라를 내뿜습니다.",
    "price": 2950000,
    "icon": "/images/items/30116.png",
    "baseStatsBonus": { "13": 30.0, "21": 20.0 },
    "combatStatsBonus": { "darkAtk": 150.0, "darkRes": 35.0, "critDmg": 25.0 },
    "grantedSkillIds": []
  },
  {
    "id": 30117,
    "name": "무저갱의 영창 비급",
    "grade": "EPIC",
    "type": "EQUIPMENT",
    "slot": "SUB_WEAPON",
    "subType": "GRIMORE",
    "description": "끝없는 구덩이 속에서 발견된 고대 암흑 마법서입니다.",
    "price": 3100000,
    "icon": "/images/items/30117.png",
    "baseStatsBonus": { "13": 45.0, "9": 5.0 },
    "combatStatsBonus": { "darkAtk": 175.0, "darkRes": 30.0, "accuracy": 20.0 },
    "grantedSkillIds": []
  },
  {
    "id": 30118,
    "name": "크툴루의 묵시록",
    "grade": "EPIC",
    "type": "EQUIPMENT",
    "slot": "SUB_WEAPON",
    "subType": "GRIMORE",
    "description": "읽는 자의 정신을 좀먹는 불길한 고서입니다. 혼돈의 정수를 담고 있습니다.",
    "price": 3400000,
    "icon": "/images/items/30118.png",
    "baseStatsBonus": { "13": 40.0, "14": 10.0 },
    "combatStatsBonus": { "chaosAtk": 150.0, "chaosRes": 30.0, "maxMp": 300.0 },
    "grantedSkillIds": []
  },
  {
    "id": 30119,
    "name": "이교도의 금기 의식서",
    "grade": "EPIC",
    "type": "EQUIPMENT",
    "slot": "SUB_WEAPON",
    "subType": "GRIMORE",
    "description": "광신도들이 인신공양을 위해 사용하던 사악한 지식이 가득합니다.",
    "price": 3600000,
    "icon": "/images/items/30119.png",
    "baseStatsBonus": { "13": 35.0, "20": 15.0 },
    "combatStatsBonus": { "chaosAtk": 170.0, "chaosRes": 25.0, "critRate": 15.0 },
    "grantedSkillIds": []
  },
  {
    "id": 30120,
    "name": "외신의 불경한 속삭임",
    "grade": "EPIC",
    "type": "EQUIPMENT",
    "slot": "SUB_WEAPON",
    "subType": "GRIMORE",
    "description": "이 세상의 것이 아닌 언어로 기록되어 있습니다. 뒤틀린 마력을 선사합니다.",
    "price": 3800000,
    "icon": "/images/items/30120.png",
    "baseStatsBonus": { "13": 50.0 },
    "combatStatsBonus": { "chaosAtk": 190.0, "chaosRes": 20.0, "magicAtk": 70.0 },
    "grantedSkillIds": []
  },
  {
    "id": 30121,
    "name": "판데믹 대백과",
    "grade": "EPIC",
    "type": "EQUIPMENT",
    "slot": "SUB_WEAPON",
    "subType": "GRIMORE",
    "description": "모든 치명적인 독소의 공식이 기록되어 있습니다. 역병의사들의 보물입니다.",
    "price": 2500000,
    "icon": "/images/items/30121.png",
    "baseStatsBonus": { "3": 30.0, "17": 20.0 },
    "combatStatsBonus": { "toxicAtk": 130.0, "toxicRes": 55.0, "accuracy": 20.0 },
    "grantedSkillIds": []
  },
  {
    "id": 30122,
    "name": "광기 어린 실험 보고서",
    "grade": "EPIC",
    "type": "EQUIPMENT",
    "slot": "SUB_WEAPON",
    "subType": "GRIMORE",
    "description": "매드 사이언티스트가 자신의 몸을 실험하며 남긴 기록입니다. 독성이 끓어오릅니다.",
    "price": 2700000,
    "icon": "/images/items/30122.png",
    "baseStatsBonus": { "3": 35.0, "13": 15.0 },
    "combatStatsBonus": { "toxicAtk": 155.0, "toxicRes": 40.0, "critRate": 12.0 },
    "grantedSkillIds": []
  },
  {
    "id": 30123,
    "name": "만독불침의 정수",
    "grade": "EPIC",
    "type": "EQUIPMENT",
    "slot": "SUB_WEAPON",
    "subType": "GRIMORE",
    "description": "세상의 모든 독을 다스리는 비법이 담겨 있습니다. 주위를 부식시키는 향기가 납니다.",
    "price": 3000000,
    "icon": "/images/items/30123.png",
    "baseStatsBonus": { "3": 45.0, "1": 5.0 },
    "combatStatsBonus": { "toxicAtk": 180.0, "toxicRes": 35.0, "statusResist": 40.0 },
    "grantedSkillIds": []
  },
  {
    "id": 30150,
    "name": "태초의 불꽃: 프로메테우스의 서",
    "grade": "LEGENDARY",
    "type": "EQUIPMENT",
    "slot": "SUB_WEAPON",
    "subType": "GRIMORE",
    "description": "인간에게 불을 가져다준 거인의 지혜가 담겨 있습니다. 영창하는 모든 화염이 태양의 온도를 갖게 됩니다.",
    "price": 15000000,
    "icon": "/images/items/30150.png",
    "baseStatsBonus": { "13": 50.0, "14": 30.0 },
    "combatStatsBonus": { "fireAtk": 450.0, "fireRes": 100.0, "magicAtk": 120.0, "critDmg": 40.0 },
    "grantedSkillIds": []
  },
  {
    "id": 30151,
    "name": "피닉스의 영생 비록",
    "grade": "LEGENDARY",
    "type": "EQUIPMENT",
    "slot": "SUB_WEAPON",
    "subType": "GRIMORE",
    "description": "죽음과 재생을 반복하는 불사조의 마력이 깃들어 있습니다. 화염은 곧 생명이 됩니다.",
    "price": 14500000,
    "icon": "/images/items/30151.png",
    "baseStatsBonus": { "13": 40.0, "1": 40.0 },
    "combatStatsBonus": { "fireAtk": 400.0, "fireRes": 150.0, "hpRegen": 50.0, "maxHp": 500.0 },
    "grantedSkillIds": []
  },
  {
    "id": 30152,
    "name": "종말의 심판: 아포칼립스 플레임",
    "grade": "LEGENDARY",
    "type": "EQUIPMENT",
    "slot": "SUB_WEAPON",
    "subType": "GRIMORE",
    "description": "세상을 불태워 정화하는 최후의 화염 마법이 기록되어 있습니다.",
    "price": 18000000,
    "icon": "/images/items/30152.png",
    "baseStatsBonus": { "13": 65.0, "20": 25.0 },
    "combatStatsBonus": { "fireAtk": 550.0, "fireRes": 80.0, "magicAtk": 150.0, "penetration": 15.0 },
    "grantedSkillIds": []
  },
  {
    "id": 30153,
    "name": "절대영도: 이미르의 눈물",
    "grade": "LEGENDARY",
    "type": "EQUIPMENT",
    "slot": "SUB_WEAPON",
    "subType": "GRIMORE",
    "description": "만물의 분자 운동을 멈추는 극한의 냉기가 서려 있습니다. 책장을 넘기면 대기가 얼어붙습니다.",
    "price": 15500000,
    "icon": "/images/items/30153.png",
    "baseStatsBonus": { "14": 55.0, "13": 25.0 },
    "combatStatsBonus": { "iceAtk": 480.0, "iceRes": 120.0, "magRes": 100.0, "statusResist": 50.0 },
    "grantedSkillIds": []
  },
  {
    "id": 30154,
    "name": "고대 빙룡의 핵 사본",
    "grade": "LEGENDARY",
    "type": "EQUIPMENT",
    "slot": "SUB_WEAPON",
    "subType": "GRIMORE",
    "description": "빙하 속에 잠든 고대 용의 정수를 문자로 형상화했습니다.",
    "price": 16000000,
    "icon": "/images/items/30154.png",
    "baseStatsBonus": { "14": 45.0, "1": 35.0 },
    "combatStatsBonus": { "iceAtk": 420.0, "iceRes": 180.0, "physDef": 150.0, "icePen": 25.0 },
    "grantedSkillIds": []
  },
  {
    "id": 30155,
    "name": "코키토스의 영원한 침묵",
    "grade": "LEGENDARY",
    "type": "EQUIPMENT",
    "slot": "SUB_WEAPON",
    "subType": "GRIMORE",
    "description": "배신자들이 갇힌 지옥 최하층의 냉기를 소환하는 금단의 마법서입니다.",
    "price": 17500000,
    "icon": "/images/items/30155.png",
    "baseStatsBonus": { "14": 70.0, "21": 20.0 },
    "combatStatsBonus": { "iceAtk": 520.0, "iceRes": 100.0, "maxMp": 800.0, "mpRegen": 15.0 },
    "grantedSkillIds": []
  },
  {
    "id": 30156,
    "name": "제우스의 벼락: 케라우노스",
    "grade": "LEGENDARY",
    "type": "EQUIPMENT",
    "slot": "SUB_WEAPON",
    "subType": "GRIMORE",
    "description": "하늘을 가르는 신의 징벌을 기록했습니다. 모든 전격 영창의 속도가 빛에 도달합니다.",
    "price": 19000000,
    "icon": "/images/items/30156.png",
    "baseStatsBonus": { "20": 60.0, "13": 30.0 },
    "combatStatsBonus": { "lightningAtk": 500.0, "lightningRes": 80.0, "critRate": 25.0, "moveSpeed": 0.5 },
    "grantedSkillIds": []
  },
  {
    "id": 30157,
    "name": "태풍의 눈: 폭풍 제어법",
    "grade": "LEGENDARY",
    "type": "EQUIPMENT",
    "slot": "SUB_WEAPON",
    "subType": "GRIMORE",
    "description": "자연의 거대한 분노인 태풍을 한 권의 책에 압축해 담았습니다.",
    "price": 16500000,
    "icon": "/images/items/30157.png",
    "baseStatsBonus": { "20": 45.0, "21": 35.0 },
    "combatStatsBonus": { "lightningAtk": 440.0, "lightningRes": 120.0, "dodge": 30.0, "accuracy": 40.0 },
    "grantedSkillIds": []
  },
  {
    "id": 30158,
    "name": "차원 간섭의 전자기 기록",
    "grade": "LEGENDARY",
    "type": "EQUIPMENT",
    "slot": "SUB_WEAPON",
    "subType": "GRIMORE",
    "description": "차원을 찢는 강력한 에너지를 전자기학적으로 재해석한 현대 마법의 정점입니다.",
    "price": 18500000,
    "icon": "/images/items/30158.png",
    "baseStatsBonus": { "20": 80.0, "14": 20.0 },
    "combatStatsBonus": { "lightningAtk": 580.0, "lightningRes": 90.0, "magicAtk": 180.0, "lightningPen": 30.0 },
    "grantedSkillIds": []
  },
  {
    "id": 30159,
    "name": "가이아의 거대한 숨결",
    "grade": "LEGENDARY",
    "type": "EQUIPMENT",
    "slot": "SUB_WEAPON",
    "subType": "GRIMORE",
    "description": "대지의 어머니가 내뱉는 박동을 기록했습니다. 산맥을 움직이는 힘을 얻게 됩니다.",
    "price": 14000000,
    "icon": "/images/items/30159.png",
    "baseStatsBonus": { "1": 60.0, "11": 40.0 },
    "combatStatsBonus": { "earthAtk": 430.0, "earthRes": 200.0, "physRes": 80.0, "physDef": 300.0 },
    "grantedSkillIds": []
  },
  {
    "id": 30160,
    "name": "고대 토템의 마스터피스",
    "grade": "LEGENDARY",
    "type": "EQUIPMENT",
    "slot": "SUB_WEAPON",
    "subType": "GRIMORE",
    "description": "수천 년 동안 전해 내려온 부족 수령들의 비기가 모두 집대성되었습니다.",
    "price": 15000000,
    "icon": "/images/items/30160.png",
    "baseStatsBonus": { "1": 50.0, "4": 50.0 },
    "combatStatsBonus": { "earthAtk": 480.0, "earthRes": 150.0, "hpRegen": 80.0, "statusResist": 60.0 },
    "grantedSkillIds": []
  },
  {
    "id": 30161,
    "name": "행성 직렬의 예언",
    "grade": "LEGENDARY",
    "type": "EQUIPMENT",
    "slot": "SUB_WEAPON",
    "subType": "GRIMORE",
    "description": "천체의 정렬이 일으키는 중력의 변화를 대지 마법으로 승화시킨 비급입니다.",
    "price": 17000000,
    "icon": "/images/items/30161.png",
    "baseStatsBonus": { "1": 70.0, "13": 30.0 },
    "combatStatsBonus": { "earthAtk": 550.0, "earthRes": 130.0, "penetration": 25.0, "accuracy": 35.0 },
    "grantedSkillIds": []
  },
  {
    "id": 30162,
    "name": "창조신의 성궤 기록",
    "grade": "LEGENDARY",
    "type": "EQUIPMENT",
    "slot": "SUB_WEAPON",
    "subType": "GRIMORE",
    "description": "빛으로 세상을 빚어낸 태초의 언어가 기록되어 있습니다. 모든 악을 소멸시킵니다.",
    "price": 20000000,
    "icon": "/images/items/30162.png",
    "baseStatsBonus": { "4": 70.0, "14": 30.0 },
    "combatStatsBonus": { "holyAtk": 500.0, "holyRes": 150.0, "maxMp": 1000.0, "mpRegen": 20.0 },
    "grantedSkillIds": []
  },
  {
    "id": 30163,
    "name": "미카엘의 심판의 종",
    "grade": "LEGENDARY",
    "type": "EQUIPMENT",
    "slot": "SUB_WEAPON",
    "subType": "GRIMORE",
    "description": "천사들의 군단장이 휘두르는 권능을 영창으로 옮겼습니다.",
    "price": 22000000,
    "icon": "/images/items/30163.png",
    "baseStatsBonus": { "4": 60.0, "13": 40.0 },
    "combatStatsBonus": { "holyAtk": 580.0, "holyRes": 120.0, "magicAtk": 200.0, "critRate": 20.0 },
    "grantedSkillIds": []
  },
  {
    "id": 30164,
    "name": "성배의 비밀 가공서",
    "grade": "LEGENDARY",
    "type": "EQUIPMENT",
    "slot": "SUB_WEAPON",
    "subType": "GRIMORE",
    "description": "신성한 보구의 에너지를 추출하여 마법으로 전환하는 기법이 담겨 있습니다.",
    "price": 19500000,
    "icon": "/images/items/30164.png",
    "baseStatsBonus": { "4": 55.0, "1": 45.0 },
    "combatStatsBonus": { "holyAtk": 460.0, "holyRes": 200.0, "hpRegen": 120.0, "maxHp": 1000.0 },
    "grantedSkillIds": []
  },
  {
    "id": 30165,
    "name": "루시퍼의 몰락한 일기",
    "grade": "LEGENDARY",
    "type": "EQUIPMENT",
    "slot": "SUB_WEAPON",
    "subType": "GRIMORE",
    "description": "가장 밝았던 천사가 가장 깊은 어둠으로 떨어지며 깨달은 금단이 적혀 있습니다.",
    "price": 21000000,
    "icon": "/images/items/30165.png",
    "baseStatsBonus": { "13": 80.0, "20": 20.0 },
    "combatStatsBonus": { "darkAtk": 550.0, "darkRes": 100.0, "magicAtk": 250.0, "darkPen": 40.0 },
    "grantedSkillIds": []
  },
  {
    "id": 30166,
    "name": "릴리스의 매혹적인 어둠",
    "grade": "LEGENDARY",
    "type": "EQUIPMENT",
    "slot": "SUB_WEAPON",
    "subType": "GRIMORE",
    "description": "밤의 여왕이 구사하던 그림자 마법의 원전입니다. 정신을 파괴하는 마력이 뿜어져 나옵니다.",
    "price": 19000000,
    "icon": "/images/items/30166.png",
    "baseStatsBonus": { "13": 60.0, "21": 40.0 },
    "combatStatsBonus": { "darkAtk": 500.0, "darkRes": 120.0, "critDmg": 60.0, "dodge": 30.0 },
    "grantedSkillIds": []
  },
  {
    "id": 30167,
    "name": "명계의 군주 하데스의 서",
    "grade": "LEGENDARY",
    "type": "EQUIPMENT",
    "slot": "SUB_WEAPON",
    "subType": "GRIMORE",
    "description": "죽은 자들의 영혼을 부리고 다스리는 명계의 질서가 기록되어 있습니다.",
    "price": 18500000,
    "icon": "/images/items/30167.png",
    "baseStatsBonus": { "13": 70.0, "15": 30.0 },
    "combatStatsBonus": { "darkAtk": 480.0, "darkRes": 180.0, "maxMp": 1200.0, "statusResist": 70.0 },
    "grantedSkillIds": []
  },
  {
    "id": 30168,
    "name": "니알라토텝의 혼돈 예찬",
    "grade": "LEGENDARY",
    "type": "EQUIPMENT",
    "slot": "SUB_WEAPON",
    "subType": "GRIMORE",
    "description": "외신의 전령이 읊조리던 기괴한 찬가입니다. 현실의 법칙을 뒤틀어버립니다.",
    "price": 25000000,
    "icon": "/images/items/30168.png",
    "baseStatsBonus": { "13": 100.0 },
    "combatStatsBonus": { "chaosAtk": 650.0, "chaosRes": 100.0, "magicAtk": 300.0, "critRate": 30.0 },
    "grantedSkillIds": []
  },
  {
    "id": 30169,
    "name": "아자토스의 잠든 의식서",
    "grade": "LEGENDARY",
    "type": "EQUIPMENT",
    "slot": "SUB_WEAPON",
    "subType": "GRIMORE",
    "description": "우주의 중심에서 꿈꾸는 눈 먼 신의 무의식이 문자로 형상화되었습니다.",
    "price": 28000000,
    "icon": "/images/items/30169.png",
    "baseStatsBonus": { "13": 60.0, "20": 40.0 },
    "combatStatsBonus": { "chaosAtk": 700.0, "chaosRes": 80.0, "chaosPen": 50.0, "accuracy": 50.0 },
    "grantedSkillIds": []
  },
  {
    "id": 30170,
    "name": "요그 소토스의 문과 열쇠",
    "grade": "LEGENDARY",
    "type": "EQUIPMENT",
    "slot": "SUB_WEAPON",
    "subType": "GRIMORE",
    "description": "과거, 현재, 미래를 아우르는 지식의 집합체입니다. 인과율을 무시하는 힘을 선사합니다.",
    "price": 30000000,
    "icon": "/images/items/30170.png",
    "baseStatsBonus": { "13": 50.0, "14": 50.0 },
    "combatStatsBonus": { "chaosAtk": 600.0, "chaosRes": 150.0, "maxMp": 2000.0, "mpRegen": 30.0 },
    "grantedSkillIds": []
  },
  {
    "id": 30171,
    "name": "생화학 병기의 기원",
    "grade": "LEGENDARY",
    "type": "EQUIPMENT",
    "slot": "SUB_WEAPON",
    "subType": "GRIMORE",
    "description": "자연에 존재하지 않는 인위적인 맹독의 정수들이 집대성되었습니다.",
    "price": 16000000,
    "icon": "/images/items/30171.png",
    "baseStatsBonus": { "3": 70.0, "17": 30.0 },
    "combatStatsBonus": { "toxicAtk": 500.0, "toxicRes": 150.0, "accuracy": 60.0, "statusResist": 80.0 },
    "grantedSkillIds": []
  },
  {
    "id": 30172,
    "name": "히드라의 맹독 혈액서",
    "grade": "LEGENDARY",
    "type": "EQUIPMENT",
    "slot": "SUB_WEAPON",
    "subType": "GRIMORE",
    "description": "머리를 자를수록 강해지는 괴수의 피를 마력화하여 페이지마다 담았습니다.",
    "price": 17000000,
    "icon": "/images/items/30172.png",
    "baseStatsBonus": { "3": 50.0, "1": 50.0 },
    "combatStatsBonus": { "toxicAtk": 550.0, "toxicRes": 120.0, "hpRegen": 150.0, "toxicPen": 40.0 },
    "grantedSkillIds": []
  },
  {
    "id": 30173,
    "name": "만물 부식의 원리",
    "grade": "LEGENDARY",
    "type": "EQUIPMENT",
    "slot": "SUB_WEAPON",
    "subType": "GRIMORE",
    "description": "금속뿐만 아니라 영혼까지 부식시키는 궁극의 독술이 기록되어 있습니다.",
    "price": 19000000,
    "icon": "/images/items/30173.png",
    "baseStatsBonus": { "3": 60.0, "13": 40.0 },
    "combatStatsBonus": { "toxicAtk": 620.0, "toxicRes": 100.0, "magicAtk": 150.0, "critRate": 25.0 },
    "grantedSkillIds": []
  }
]